{"entities":{"d2981294-6353-4ff0-8c7e-231fa228522b":{"enabled":true,"tags":[],"children":["fcf48691-f239-4de5-a454-9f5870ea4fb0","ec8a2565-0553-4f25-991b-b654b94ac3e8"],"position":[0,0,0],"rotation":[0,0,0],"scale":[0.01,0.01,0.01],"resource_id":"d2981294-6353-4ff0-8c7e-231fa228522b","name":"RootNode","components":{},"parent":null},"fcf48691-f239-4de5-a454-9f5870ea4fb0":{"enabled":true,"tags":[],"children":[],"position":[0,0,0],"rotation":[-90,0,0],"scale":[100,100,100],"resource_id":"fcf48691-f239-4de5-a454-9f5870ea4fb0","name":"Cube","components":{"render":{"enabled":true,"type":"asset","asset":236071658,"materialAssets":[236071655],"layers":[0],"batchGroupId":null,"castShadows":true,"castShadowsLightmap":true,"receiveShadows":true,"lightmapped":false,"lightmapSizeMultiplier":1,"castShadowsLightMap":true,"lightMapped":false,"lightMapSizeMultiplier":1,"isStatic":false,"rootBone":null}},"parent":"d2981294-6353-4ff0-8c7e-231fa228522b"},"ec8a2565-0553-4f25-991b-b654b94ac3e8":{"enabled":true,"tags":[],"children":[],"position":[0,24.9298,-21.3239],"rotation":[-90,0,0],"scale":[100,100,100],"resource_id":"ec8a2565-0553-4f25-991b-b654b94ac3e8","name":"Cube.001","components":{"render":{"enabled":true,"type":"asset","asset":236071659,"materialAssets":[236071656],"layers":[0],"batchGroupId":null,"castShadows":true,"castShadowsLightmap":true,"receiveShadows":true,"lightmapped":false,"lightmapSizeMultiplier":1,"castShadowsLightMap":true,"lightMapped":false,"lightMapSizeMultiplier":1,"isStatic":false,"rootBone":null}},"parent":"d2981294-6353-4ff0-8c7e-231fa228522b"}}}