{"entities":{"135249ed-0e56-4310-9d1d-442ff9ade2b9":{"name":"La Vaca Saturno Saturnita","tags":[],"enabled":true,"resource_id":"135249ed-0e56-4310-9d1d-442ff9ade2b9","parent":null,"children":["3d67816e-537b-4ac3-9b4f-f9c2c9298783"],"position":[26.564022064208984,6.445,-8.551085472106934],"rotation":[180,-50.07460873189686,180],"scale":[1,1,1],"components":{"script":{"enabled":true,"order":["rotate"],"scripts":{"rotate":{"enabled":true,"attributes":{"speed":-20,"rotationDir":"y","upDown":false,"upDownAmount":0.25}}}}}},"3d67816e-537b-4ac3-9b4f-f9c2c9298783":{"name":"Transform","tags":[],"enabled":true,"resource_id":"3d67816e-537b-4ac3-9b4f-f9c2c9298783","parent":"135249ed-0e56-4310-9d1d-442ff9ade2b9","children":["1437b509-185a-4ccb-9c34-3cf916ea212c"],"position":[0.000027284957468509674,0.6137073071803343,-0.000047801120672374964],"rotation":[0,0,0],"scale":[0.014,0.014,0.014],"components":{}},"1437b509-185a-4ccb-9c34-3cf916ea212c":{"name":"Body","tags":[],"enabled":true,"resource_id":"1437b509-185a-4ccb-9c34-3cf916ea212c","parent":"3d67816e-537b-4ac3-9b4f-f9c2c9298783","children":[],"position":[-3.202036695358923,24.817679157292197,-0.28050765063825095],"rotation":[-90.00000000060238,0,4.6258535474754114e-7],"scale":[350,350,350],"components":{"render":{"enabled":true,"type":"asset","asset":232228209,"materialAssets":[232228238],"layers":[1002],"batchGroupId":null,"castShadows":true,"castShadowsLightmap":true,"receiveShadows":true,"lightmapped":false,"lightmapSizeMultiplier":1,"castShadowsLightMap":true,"lightMapped":false,"lightMapSizeMultiplier":1,"isStatic":false,"rootBone":null}}}}}