{"scale":1,"offsetX":0,"offsetY":0,"screwScale":1,"layers":[{"pos":{"x":0,"y":0,"z":0},"angle":0,"bars":[{"pos":{"x":0,"y":-1.25,"z":0},"angle":0,"img":"ScrewJamShapes (19)","color":"#FFFFFF80","screws":[{"pos":{"x":1.8799999952316284,"y":1,"z":0},"img":"Screw 7","isStar":false,"isIce":false,"isShutter":false,"z_initGame":0,"uid_initGame":0,"check_box":0,"delay":false,"uid_Unlock":0,"screw_uid":0,"frame":0,"uid_class":2533,"click_one":false,"special1":0,"special2":0,"special3":0,"special4":0,"special5":0,"special6":0,"typeSpecial1":0,"typeSpecial2":3,"typeSpecial3":0,"typeSpecial4":6,"typeSpecial5":0,"typeSpecial6":0,"checkPullUpScrews":false,"ropeUid":-1,"index":0,"bar":0,"barW":0,"barH":0,"barPosY":0,"barPosX":0,"posX":457,"posY":588,"keyLayer":0,"xx":457,"yy":588,"id":0,"uidScrew":2534},{"pos":{"x":-1.75,"y":1,"z":0},"img":"Screw 7","isStar":false,"isIce":false,"isShutter":false,"z_initGame":0,"uid_initGame":0,"check_box":0,"delay":false,"uid_Unlock":0,"screw_uid":0,"frame":0,"uid_class":2533,"click_one":false,"special1":0,"special2":0,"special3":0,"special4":0,"special5":0,"special6":0,"typeSpecial1":0,"typeSpecial2":3,"typeSpecial3":0,"typeSpecial4":6,"typeSpecial5":0,"typeSpecial6":0,"checkPullUpScrews":false,"ropeUid":-1,"index":1,"bar":0,"barW":0,"barH":0,"barPosY":0,"barPosX":0,"posX":269,"posY":588,"keyLayer":0,"xx":269,"yy":588,"id":0,"uidScrew":2538},{"pos":{"x":1.8799999952316284,"y":-3.5,"z":0},"img":"Screw 7","isStar":false,"isIce":false,"isShutter":false,"z_initGame":0,"uid_initGame":0,"check_box":0,"delay":false,"uid_Unlock":0,"screw_uid":0,"frame":0,"uid_class":2533,"click_one":false,"special1":0,"special2":0,"special3":0,"special4":0,"special5":0,"special6":0,"typeSpecial1":0,"typeSpecial2":3,"typeSpecial3":0,"typeSpecial4":6,"typeSpecial5":0,"typeSpecial6":0,"checkPullUpScrews":false,"ropeUid":-1,"index":2,"bar":0,"barW":0,"barH":0,"barPosY":0,"barPosX":0,"posX":457,"posY":822,"keyLayer":0,"xx":457,"yy":822,"id":0,"uidScrew":2542},{"pos":{"x":-1.75,"y":-3.5,"z":0},"img":"Screw 0","isStar":false,"isIce":false,"isShutter":false,"z_initGame":0,"uid_initGame":0,"check_box":0,"delay":false,"uid_Unlock":0,"screw_uid":0,"frame":0,"uid_class":2533,"click_one":false,"special1":0,"special2":0,"special3":0,"special4":0,"special5":0,"special6":0,"typeSpecial1":0,"typeSpecial2":3,"typeSpecial3":0,"typeSpecial4":6,"typeSpecial5":0,"typeSpecial6":0,"checkPullUpScrews":false,"ropeUid":-1,"index":3,"bar":0,"barW":0,"barH":0,"barPosY":0,"barPosX":0,"posX":269,"posY":822,"keyLayer":0,"xx":269,"yy":822,"id":0,"uidScrew":2546},{"pos":{"x":0.75,"y":-1.25,"z":0},"img":"Screw 0","isStar":false,"isIce":false,"isShutter":false,"z_initGame":0,"uid_initGame":0,"check_box":0,"delay":false,"uid_Unlock":0,"screw_uid":0,"frame":0,"uid_class":2533,"click_one":false,"special1":0,"special2":0,"special3":0,"special4":0,"special5":0,"special6":0,"typeSpecial1":0,"typeSpecial2":3,"typeSpecial3":0,"typeSpecial4":6,"typeSpecial5":0,"typeSpecial6":0,"checkPullUpScrews":false,"ropeUid":-1,"index":4,"bar":0,"barW":0,"barH":0,"barPosY":0,"barPosX":0,"posX":399,"posY":705,"keyLayer":0,"xx":399,"yy":705,"id":0,"uidScrew":2550},{"pos":{"x":-0.75,"y":-1.25,"z":0},"img":"Screw 0","isStar":false,"isIce":false,"isShutter":false,"z_initGame":0,"uid_initGame":0,"check_box":0,"delay":false,"uid_Unlock":0,"screw_uid":0,"frame":0,"uid_class":2533,"click_one":false,"special1":0,"special2":0,"special3":0,"special4":0,"special5":0,"special6":0,"typeSpecial1":0,"typeSpecial2":3,"typeSpecial3":0,"typeSpecial4":6,"typeSpecial5":0,"typeSpecial6":0,"checkPullUpScrews":false,"ropeUid":-1,"index":5,"bar":0,"barW":0,"barH":0,"barPosY":0,"barPosX":0,"posX":321,"posY":705,"keyLayer":0,"xx":321,"yy":705,"id":0,"uidScrew":2554}],"shape":{"colorHex":"7, 184, 11 ","posX":360,"posY":705,"sizeW":407,"sizeH":407,"name":"ScrewJamShapes19","angles":0,"bar":0,"colorValues":-281492157629439,"indexBar":0}}]},{"pos":{"x":0,"y":0,"z":0},"angle":0,"bars":[{"pos":{"x":-1.0490381717681885,"y":0.013012886047363281,"z":0},"angle":60.000003814697266,"img":"ScrewJamShapes (2)","color":"#FFFFFF80","screws":[{"pos":{"x":0.5099999904632568,"y":-0.8799999952316284,"z":0},"img":"Screw 2","isStar":false,"isIce":false,"isShutter":false,"z_initGame":0,"uid_initGame":0,"check_box":0,"delay":false,"uid_Unlock":0,"screw_uid":0,"frame":0,"uid_class":2559,"click_one":false,"special1":0,"special2":0,"special3":0,"special4":0,"special5":0,"special6":0,"typeSpecial1":0,"typeSpecial2":3,"typeSpecial3":0,"typeSpecial4":6,"typeSpecial5":0,"typeSpecial6":0,"checkPullUpScrews":false,"ropeUid":-1,"index":0,"bar":0,"barW":0,"barH":0,"barPosY":0,"barPosX":0,"posX":386,"posY":685,"keyLayer":1,"xx":386,"yy":685,"id":0,"uidScrew":2560},{"pos":{"x":-4.440000534057617,"y":-2.309999942779541,"z":0},"img":"Screw 4","isStar":false,"isIce":false,"isShutter":false,"z_initGame":0,"uid_initGame":0,"check_box":0,"delay":false,"uid_Unlock":0,"screw_uid":0,"frame":0,"uid_class":2559,"click_one":false,"special1":0,"special2":0,"special3":0,"special4":0,"special5":0,"special6":0,"typeSpecial1":0,"typeSpecial2":3,"typeSpecial3":0,"typeSpecial4":6,"typeSpecial5":0,"typeSpecial6":0,"checkPullUpScrews":false,"ropeUid":-1,"index":1,"bar":0,"barW":0,"barH":0,"barPosY":0,"barPosX":0,"posX":129,"posY":760,"keyLayer":1,"xx":129,"yy":760,"id":0,"uidScrew":2564},{"pos":{"x":0.7900002002716064,"y":3.3600003719329834,"z":0},"img":"Screw 1","isStar":false,"isIce":false,"isShutter":false,"z_initGame":0,"uid_initGame":0,"check_box":0,"delay":false,"uid_Unlock":0,"screw_uid":0,"frame":0,"uid_class":2559,"click_one":false,"special1":0,"special2":0,"special3":0,"special4":0,"special5":0,"special6":0,"typeSpecial1":0,"typeSpecial2":3,"typeSpecial3":0,"typeSpecial4":6,"typeSpecial5":0,"typeSpecial6":0,"checkPullUpScrews":false,"ropeUid":-1,"index":2,"bar":0,"barW":0,"barH":0,"barPosY":0,"barPosX":0,"posX":401,"posY":465,"keyLayer":1,"xx":401,"yy":465,"id":0,"uidScrew":2568},{"pos":{"x":-0.9200000166893005,"y":-0.030000008642673492,"z":0},"img":"Screw 9","isStar":false,"isIce":false,"isShutter":false,"z_initGame":0,"uid_initGame":0,"check_box":0,"delay":false,"uid_Unlock":0,"screw_uid":0,"frame":0,"uid_class":2559,"click_one":false,"special1":0,"special2":0,"special3":0,"special4":0,"special5":0,"special6":0,"typeSpecial1":0,"typeSpecial2":3,"typeSpecial3":0,"typeSpecial4":6,"typeSpecial5":0,"typeSpecial6":0,"checkPullUpScrews":false,"ropeUid":-1,"index":3,"bar":0,"barW":0,"barH":0,"barPosY":0,"barPosX":0,"posX":312,"posY":641,"keyLayer":1,"xx":312,"yy":641,"id":0,"uidScrew":2572},{"pos":{"x":-0.8199995756149292,"y":4.109999656677246,"z":0},"img":"Screw 3","isStar":false,"isIce":false,"isShutter":false,"z_initGame":0,"uid_initGame":0,"check_box":0,"delay":false,"uid_Unlock":0,"screw_uid":0,"frame":0,"uid_class":2559,"click_one":false,"special1":0,"special2":0,"special3":0,"special4":0,"special5":0,"special6":0,"typeSpecial1":0,"typeSpecial2":3,"typeSpecial3":0,"typeSpecial4":6,"typeSpecial5":0,"typeSpecial6":0,"checkPullUpScrews":false,"ropeUid":-1,"index":4,"bar":0,"barW":0,"barH":0,"barPosY":0,"barPosX":0,"posX":317,"posY":426,"keyLayer":1,"xx":317,"yy":426,"id":0,"uidScrew":2576},{"pos":{"x":2.4900002479553223,"y":2.4299988746643066,"z":0},"img":"Screw 8","isStar":false,"isIce":false,"isShutter":false,"z_initGame":0,"uid_initGame":0,"check_box":0,"delay":false,"uid_Unlock":0,"screw_uid":0,"frame":0,"uid_class":2559,"click_one":false,"special1":0,"special2":0,"special3":0,"special4":0,"special5":0,"special6":0,"typeSpecial1":0,"typeSpecial2":3,"typeSpecial3":0,"typeSpecial4":6,"typeSpecial5":0,"typeSpecial6":0,"checkPullUpScrews":false,"ropeUid":-1,"index":5,"bar":0,"barW":0,"barH":0,"barPosY":0,"barPosX":0,"posX":489,"posY":513,"keyLayer":1,"xx":489,"yy":513,"id":0,"uidScrew":2580},{"pos":{"x":-2.559999465942383,"y":0.7599997520446777,"z":0},"img":"Screw 1","isStar":false,"isIce":false,"isShutter":false,"z_initGame":0,"uid_initGame":0,"check_box":0,"delay":false,"uid_Unlock":0,"screw_uid":0,"frame":0,"uid_class":2559,"click_one":false,"special1":0,"special2":0,"special3":0,"special4":0,"special5":0,"special6":0,"typeSpecial1":0,"typeSpecial2":3,"typeSpecial3":0,"typeSpecial4":6,"typeSpecial5":0,"typeSpecial6":0,"checkPullUpScrews":false,"ropeUid":-1,"index":6,"bar":0,"barW":0,"barH":0,"barPosY":0,"barPosX":0,"posX":226,"posY":600,"keyLayer":1,"xx":226,"yy":600,"id":0,"uidScrew":2584}],"shape":{"colorHex":"15, 175, 255 ","posX":305.4500150680542,"posY":639.3233299255371,"sizeW":498,"sizeH":308,"name":"ScrewJamShapes2","angles":299.99999618530273,"bar":1,"colorValues":-281492157629439,"indexBar":0}},{"pos":{"x":3.4306042194366455,"y":-3.7280168533325195,"z":0},"angle":329.99993896484375,"img":"ScrewJamShapes (27)","color":"#FFFFFF80","screws":[{"pos":{"x":2.4000000953674316,"y":-3.059999942779541,"z":0},"img":"Screw 3","isStar":false,"isIce":false,"isShutter":false,"z_initGame":0,"uid_initGame":0,"check_box":0,"delay":false,"uid_Unlock":0,"screw_uid":0,"frame":0,"uid_class":2589,"click_one":false,"special1":0,"special2":0,"special3":0,"special4":0,"special5":0,"special6":0,"typeSpecial1":0,"typeSpecial2":3,"typeSpecial3":0,"typeSpecial4":6,"typeSpecial5":0,"typeSpecial6":0,"checkPullUpScrews":false,"ropeUid":-1,"index":0,"bar":1,"barW":0,"barH":0,"barPosY":0,"barPosX":0,"posX":484,"posY":799,"keyLayer":1,"xx":484,"yy":799,"id":0,"uidScrew":2590},{"pos":{"x":4.550000190734863,"y":-4.429999828338623,"z":0},"img":"Screw 8","isStar":false,"isIce":false,"isShutter":false,"z_initGame":0,"uid_initGame":0,"check_box":0,"delay":false,"uid_Unlock":0,"screw_uid":0,"frame":0,"uid_class":2589,"click_one":false,"special1":0,"special2":0,"special3":0,"special4":0,"special5":0,"special6":0,"typeSpecial1":0,"typeSpecial2":3,"typeSpecial3":0,"typeSpecial4":6,"typeSpecial5":0,"typeSpecial6":0,"checkPullUpScrews":false,"ropeUid":-1,"index":1,"bar":1,"barW":0,"barH":0,"barPosY":0,"barPosX":0,"posX":596,"posY":870,"keyLayer":1,"xx":596,"yy":870,"id":0,"uidScrew":2594},{"pos":{"x":2.9800000190734863,"y":-7.5,"z":0},"img":"Screw 2","isStar":false,"isIce":false,"isShutter":false,"z_initGame":0,"uid_initGame":0,"check_box":0,"delay":false,"uid_Unlock":0,"screw_uid":0,"frame":0,"uid_class":2589,"click_one":false,"special1":0,"special2":0,"special3":0,"special4":0,"special5":0,"special6":0,"typeSpecial1":0,"typeSpecial2":3,"typeSpecial3":0,"typeSpecial4":6,"typeSpecial5":0,"typeSpecial6":0,"checkPullUpScrews":false,"ropeUid":-1,"index":2,"bar":1,"barW":0,"barH":0,"barPosY":0,"barPosX":0,"posX":514,"posY":1030,"keyLayer":1,"xx":514,"yy":1030,"id":0,"uidScrew":2598}],"shape":{"colorHex":"15, 175, 255 ","posX":538.3914194107056,"posY":833.856876373291,"sizeW":290,"sizeH":531,"name":"ScrewJamShapes27","angles":30.000061035156254,"bar":1,"colorValues":-281492157629439,"indexBar":1}},{"pos":{"x":0.006564661860466003,"y":-6.6586222648620605,"z":0},"angle":149.99996948242188,"img":"ScrewJamShapes (33)","color":"#FFFFFF80","screws":[{"pos":{"x":-2.25,"y":-6.71999979019165,"z":0},"img":"Screw 4","isStar":false,"isIce":false,"isShutter":false,"z_initGame":0,"uid_initGame":0,"check_box":0,"delay":false,"uid_Unlock":0,"screw_uid":0,"frame":0,"uid_class":2603,"click_one":false,"special1":0,"special2":0,"special3":0,"special4":0,"special5":0,"special6":0,"typeSpecial1":0,"typeSpecial2":3,"typeSpecial3":0,"typeSpecial4":6,"typeSpecial5":0,"typeSpecial6":0,"checkPullUpScrews":false,"ropeUid":-1,"index":0,"bar":2,"barW":0,"barH":0,"barPosY":0,"barPosX":0,"posX":243,"posY":989,"keyLayer":1,"xx":243,"yy":989,"id":0,"uidScrew":2604},{"pos":{"x":1.1299998760223389,"y":-8.670000076293945,"z":0},"img":"Screw 9","isStar":false,"isIce":false,"isShutter":false,"z_initGame":0,"uid_initGame":0,"check_box":0,"delay":false,"uid_Unlock":0,"screw_uid":0,"frame":0,"uid_class":2603,"click_one":false,"special1":0,"special2":0,"special3":0,"special4":0,"special5":0,"special6":0,"typeSpecial1":0,"typeSpecial2":3,"typeSpecial3":0,"typeSpecial4":6,"typeSpecial5":0,"typeSpecial6":0,"checkPullUpScrews":false,"ropeUid":-1,"index":1,"bar":2,"barW":0,"barH":0,"barPosY":0,"barPosX":0,"posX":418,"posY":1090,"keyLayer":1,"xx":418,"yy":1090,"id":0,"uidScrew":2608}],"shape":{"colorHex":"15, 175, 255 ","posX":360.34136241674423,"posY":986.2483577728271,"sizeW":333,"sizeH":248.00000000000003,"name":"ScrewJamShapes33","angles":210.0000305175781,"bar":1,"colorValues":-281492157629439,"indexBar":2}}]},{"pos":{"x":0,"y":0,"z":0},"angle":0,"bars":[{"pos":{"x":-1.7699999809265137,"y":2.559999942779541,"z":0},"angle":240.00003051757812,"img":"ScrewJamShapes (30)","color":"#FFFFFF80","screws":[{"pos":{"x":-0.4999997615814209,"y":0.7499995231628418,"z":0},"img":"Screw 5","isStar":false,"isIce":false,"isShutter":false,"z_initGame":0,"uid_initGame":0,"check_box":0,"delay":false,"uid_Unlock":0,"screw_uid":0,"frame":0,"uid_class":2613,"click_one":false,"special1":0,"special2":0,"special3":0,"special4":0,"special5":0,"special6":0,"typeSpecial1":0,"typeSpecial2":3,"typeSpecial3":0,"typeSpecial4":6,"typeSpecial5":0,"typeSpecial6":0,"checkPullUpScrews":false,"ropeUid":-1,"index":0,"bar":0,"barW":0,"barH":0,"barPosY":0,"barPosX":0,"posX":334,"posY":601,"keyLayer":2,"xx":334,"yy":601,"id":0,"uidScrew":2614},{"pos":{"x":-3.750000476837158,"y":2.75,"z":0},"img":"Screw 6","isStar":false,"isIce":false,"isShutter":false,"z_initGame":0,"uid_initGame":0,"check_box":0,"delay":false,"uid_Unlock":0,"screw_uid":0,"frame":0,"uid_class":2613,"click_one":false,"special1":0,"special2":0,"special3":0,"special4":0,"special5":0,"special6":0,"typeSpecial1":0,"typeSpecial2":3,"typeSpecial3":0,"typeSpecial4":6,"typeSpecial5":0,"typeSpecial6":0,"checkPullUpScrews":false,"ropeUid":-1,"index":1,"bar":0,"barW":0,"barH":0,"barPosY":0,"barPosX":0,"posX":164,"posY":496,"keyLayer":2,"xx":164,"yy":497,"id":0,"uidScrew":2618},{"pos":{"x":-3.000000476837158,"y":4.250000476837158,"z":0},"img":"Screw 2","isStar":false,"isIce":false,"isShutter":false,"z_initGame":0,"uid_initGame":0,"check_box":0,"delay":false,"uid_Unlock":0,"screw_uid":0,"frame":0,"uid_class":2613,"click_one":false,"special1":0,"special2":0,"special3":0,"special4":0,"special5":0,"special6":0,"typeSpecial1":0,"typeSpecial2":3,"typeSpecial3":0,"typeSpecial4":6,"typeSpecial5":0,"typeSpecial6":0,"checkPullUpScrews":false,"ropeUid":-1,"index":2,"bar":0,"barW":0,"barH":0,"barPosY":0,"barPosX":0,"posX":203,"posY":418,"keyLayer":2,"xx":203,"yy":418,"id":0,"uidScrew":2622}],"shape":{"colorHex":"255, 156, 0 ","posX":267.9600009918213,"posY":506.88000297546387,"sizeW":223.00000000000003,"sizeH":329,"name":"ScrewJamShapes30","angles":119.99996948242188,"bar":2,"colorValues":-281492157629439,"indexBar":0}},{"pos":{"x":2.4992685317993164,"y":1.1157538890838623,"z":0},"angle":14.999959945678711,"img":"ScrewJamShapes (30)","color":"#FFFFFF80","screws":[{"pos":{"x":2.190000534057617,"y":-0.8999996185302734,"z":0},"img":"Screw 9","isStar":false,"isIce":false,"isShutter":false,"z_initGame":0,"uid_initGame":0,"check_box":0,"delay":false,"uid_Unlock":0,"screw_uid":0,"frame":0,"uid_class":2627,"click_one":false,"special1":0,"special2":0,"special3":0,"special4":0,"special5":0,"special6":0,"typeSpecial1":0,"typeSpecial2":3,"typeSpecial3":0,"typeSpecial4":6,"typeSpecial5":0,"typeSpecial6":0,"checkPullUpScrews":false,"ropeUid":-1,"index":0,"bar":1,"barW":0,"barH":0,"barPosY":0,"barPosX":0,"posX":473,"posY":686,"keyLayer":2,"xx":473,"yy":686,"id":0,"uidScrew":2628},{"pos":{"x":3.180000066757202,"y":2.1700000762939453,"z":0},"img":"Screw 5","isStar":false,"isIce":false,"isShutter":false,"z_initGame":0,"uid_initGame":0,"check_box":0,"delay":false,"uid_Unlock":0,"screw_uid":0,"frame":0,"uid_class":2627,"click_one":false,"special1":0,"special2":0,"special3":0,"special4":0,"special5":0,"special6":0,"typeSpecial1":0,"typeSpecial2":3,"typeSpecial3":0,"typeSpecial4":6,"typeSpecial5":0,"typeSpecial6":0,"checkPullUpScrews":false,"ropeUid":-1,"index":1,"bar":1,"barW":0,"barH":0,"barPosY":0,"barPosX":0,"posX":525,"posY":527,"keyLayer":2,"xx":525,"yy":527,"id":0,"uidScrew":2632},{"pos":{"x":3.759999990463257,"y":-0.38999998569488525,"z":0},"img":"Screw 1","isStar":false,"isIce":false,"isShutter":false,"z_initGame":0,"uid_initGame":0,"check_box":0,"delay":false,"uid_Unlock":0,"screw_uid":0,"frame":0,"uid_class":2627,"click_one":false,"special1":0,"special2":0,"special3":0,"special4":0,"special5":0,"special6":0,"typeSpecial1":0,"typeSpecial2":3,"typeSpecial3":0,"typeSpecial4":6,"typeSpecial5":0,"typeSpecial6":0,"checkPullUpScrews":false,"ropeUid":-1,"index":2,"bar":1,"barW":0,"barH":0,"barPosY":0,"barPosX":0,"posX":555,"posY":660,"keyLayer":2,"xx":555,"yy":660,"id":0,"uidScrew":2636}],"shape":{"colorHex":"255, 156, 0 ","posX":489.96196365356445,"posY":581.9807977676392,"sizeW":223.00000000000003,"sizeH":329,"name":"ScrewJamShapes30","angles":345.0000400543213,"bar":2,"colorValues":-281492157629439,"indexBar":1}},{"pos":{"x":-2.753882884979248,"y":-2.3925626277923584,"z":0},"angle":44.999969482421875,"img":"ScrewJamShapes (30)","color":"#FFFFFF80","screws":[{"pos":{"x":-3.380000114440918,"y":-0.3599998950958252,"z":0},"img":"Screw 8","isStar":false,"isIce":false,"isShutter":false,"z_initGame":0,"uid_initGame":0,"check_box":0,"delay":false,"uid_Unlock":0,"screw_uid":0,"frame":0,"uid_class":2641,"click_one":false,"special1":0,"special2":0,"special3":0,"special4":0,"special5":0,"special6":0,"typeSpecial1":0,"typeSpecial2":3,"typeSpecial3":0,"typeSpecial4":6,"typeSpecial5":0,"typeSpecial6":0,"checkPullUpScrews":false,"ropeUid":-1,"index":0,"bar":2,"barW":0,"barH":0,"barPosY":0,"barPosX":0,"posX":184,"posY":658,"keyLayer":2,"xx":184,"yy":658,"id":0,"uidScrew":2642},{"pos":{"x":-1.9799998998641968,"y":-4.390000343322754,"z":0},"img":"Screw 3","isStar":false,"isIce":false,"isShutter":false,"z_initGame":0,"uid_initGame":0,"check_box":0,"delay":false,"uid_Unlock":0,"screw_uid":0,"frame":0,"uid_class":2641,"click_one":false,"special1":0,"special2":0,"special3":0,"special4":0,"special5":0,"special6":0,"typeSpecial1":0,"typeSpecial2":3,"typeSpecial3":0,"typeSpecial4":6,"typeSpecial5":0,"typeSpecial6":0,"checkPullUpScrews":false,"ropeUid":-1,"index":1,"bar":2,"barW":0,"barH":0,"barPosY":0,"barPosX":0,"posX":257,"posY":868,"keyLayer":2,"xx":257,"yy":868,"id":0,"uidScrew":2646}],"shape":{"colorHex":"255, 156, 0 ","posX":216.7980899810791,"posY":764.4132566452026,"sizeW":223.00000000000003,"sizeH":329,"name":"ScrewJamShapes30","angles":315.0000305175781,"bar":2,"colorValues":-281492157629439,"indexBar":2}},{"pos":{"x":2.990000009536743,"y":-5.590000152587891,"z":0},"angle":330.00006103515625,"img":"ScrewJamShapes (8)","color":"#FFFFFF80","screws":[{"pos":{"x":3.0399999618530273,"y":-3.5299999713897705,"z":0},"img":"Screw 5","isStar":false,"isIce":false,"isShutter":false,"z_initGame":0,"uid_initGame":0,"check_box":0,"delay":false,"uid_Unlock":0,"screw_uid":0,"frame":0,"uid_class":2651,"click_one":false,"special1":0,"special2":0,"special3":0,"special4":0,"special5":0,"special6":0,"typeSpecial1":0,"typeSpecial2":3,"typeSpecial3":0,"typeSpecial4":6,"typeSpecial5":0,"typeSpecial6":0,"checkPullUpScrews":false,"ropeUid":-1,"index":0,"bar":3,"barW":0,"barH":0,"barPosY":0,"barPosX":0,"posX":518,"posY":823,"keyLayer":2,"xx":518,"yy":823,"id":0,"uidScrew":2652},{"pos":{"x":2.2899999618530273,"y":-4.779999732971191,"z":0},"img":"Screw 6","isStar":false,"isIce":false,"isShutter":false,"z_initGame":0,"uid_initGame":0,"check_box":0,"delay":false,"uid_Unlock":0,"screw_uid":0,"frame":0,"uid_class":2651,"click_one":false,"special1":0,"special2":0,"special3":0,"special4":0,"special5":0,"special6":0,"typeSpecial1":0,"typeSpecial2":3,"typeSpecial3":0,"typeSpecial4":6,"typeSpecial5":0,"typeSpecial6":0,"checkPullUpScrews":false,"ropeUid":-1,"index":1,"bar":3,"barW":0,"barH":0,"barPosY":0,"barPosX":0,"posX":479,"posY":888,"keyLayer":2,"xx":479,"yy":888,"id":0,"uidScrew":2656},{"pos":{"x":1.5399999618530273,"y":-6.029999732971191,"z":0},"img":"Screw 6","isStar":false,"isIce":false,"isShutter":false,"z_initGame":0,"uid_initGame":0,"check_box":0,"delay":false,"uid_Unlock":0,"screw_uid":0,"frame":0,"uid_class":2651,"click_one":false,"special1":0,"special2":0,"special3":0,"special4":0,"special5":0,"special6":0,"typeSpecial1":0,"typeSpecial2":3,"typeSpecial3":0,"typeSpecial4":6,"typeSpecial5":0,"typeSpecial6":0,"checkPullUpScrews":false,"ropeUid":-1,"index":2,"bar":3,"barW":0,"barH":0,"barPosY":0,"barPosX":0,"posX":440,"posY":953,"keyLayer":2,"xx":440,"yy":953,"id":0,"uidScrew":2660},{"pos":{"x":2.869999885559082,"y":-7.639999866485596,"z":0},"img":"Screw 4","isStar":false,"isIce":false,"isShutter":false,"z_initGame":0,"uid_initGame":0,"check_box":0,"delay":false,"uid_Unlock":0,"screw_uid":0,"frame":0,"uid_class":2651,"click_one":false,"special1":0,"special2":0,"special3":0,"special4":0,"special5":0,"special6":0,"typeSpecial1":0,"typeSpecial2":3,"typeSpecial3":0,"typeSpecial4":6,"typeSpecial5":0,"typeSpecial6":0,"checkPullUpScrews":false,"ropeUid":-1,"index":3,"bar":3,"barW":0,"barH":0,"barPosY":0,"barPosX":0,"posX":509,"posY":1037,"keyLayer":2,"xx":509,"yy":1037,"id":0,"uidScrew":2664}],"shape":{"colorHex":"255, 156, 0 ","posX":515.4800004959106,"posY":930.6800079345703,"sizeW":222,"sizeH":326.99999999999994,"name":"ScrewJamShapes8","angles":29.99993896484375,"bar":2,"colorValues":-281492157629439,"indexBar":3}}]}],"box":[{"level":1,"box_frame":"5,9,3,7,6,4,0,1,8,2","total_box_quantity":"3,3,3,3,3,3,3,3,3,3","child_box":["0,0,0","0,0,0","0,0,0","0,0,0","0,0,0","0,0,0","0,0,0","0,0,0","0,0,0","0,0,0"]}]}